avalon_sdk_direct/__init__.py
avalon_sdk_direct/jrpc_work_order.py
avalon_sdk_direct/jrpc_work_order_receipt.py
avalon_sdk_direct/jrpc_worker_registry.py
avalon_sdk_py-0.1.dist-info/DESCRIPTION.rst
avalon_sdk_py-0.1.dist-info/METADATA
avalon_sdk_py-0.1.dist-info/RECORD
avalon_sdk_py-0.1.dist-info/WHEEL
avalon_sdk_py-0.1.dist-info/metadata.json
avalon_sdk_py-0.1.dist-info/top_level.txt
enums/__init__.py
enums/error_code.py
enums/worker.py
exceptions/__init__.py
exceptions/invalid_parameter.py
exceptions/unknown_error.py
handler/__init__.py
handler/error_handler.py
handler/http_jrpc_client.py
interfaces/__init__.py
interfaces/work_order.py
interfaces/work_order_proxy.py
interfaces/work_order_receipt.py
interfaces/worker_registry.py
interfaces/worker_registry_list.py
validation/__init__.py
validation/argument_validator.py
validation/json_validator.py
validation/data/WorkOrderGetResult.json
validation/data/WorkOrderReceiptCreate.json
validation/data/WorkOrderReceiptLookUp.json
validation/data/WorkOrderReceiptLookUpNext.json
validation/data/WorkOrderReceiptRetrieve.json
validation/data/WorkOrderReceiptUpdate.json
validation/data/WorkOrderReceiptUpdateRetrieve.json
validation/data/WorkOrderSubmit.json
validation/data/WorkerLookUp.json
validation/data/WorkerLookUpNext.json
validation/data/WorkerRetrieve.json
validation/data/inData.json
validation/data/json_rpc.json
validation/data/sdk_WorkOrderSubmit.json
